spp_localSQL/Operation.py
spp_localSQL/__init__.py
spp_localSQL-0.2.2.dist-info/METADATA
spp_localSQL-0.2.2.dist-info/WHEEL
spp_localSQL-0.2.2.dist-info/top_level.txt
spp_localSQL-0.2.2.dist-info/RECORD
