Metadata-Version: 2.1
Name: spp_localSQL
Version: 0.2.2
Summary: 一个简单的 SQLite 数据库助手类
Home-page: https://gitee.com/liehuozhuoxin/local-database-operations
Author: ShiPanPan
Author-email: 417833515@qq.com
Classifier: Programming Language :: Python :: 3
Classifier: License :: OSI Approved :: MIT License
Classifier: Operating System :: OS Independent
Requires-Python: >=3.6
